Metadata-Version: 2.1
Name: distripkg
Version: 0.9
Summary: Gaussian and Binomial distributions from udacity
Home-page: UNKNOWN
Author: Amos Omofaiye
Author-email: shema.omofaye@gmail.com
License: UNKNOWN
Platform: UNKNOWN
License-File: license.txt
